solidwebpush/__init__.py
solidwebpush-1.2.3.dist-info/METADATA
solidwebpush-1.2.3.dist-info/RECORD
solidwebpush-1.2.3.dist-info/WHEEL
solidwebpush-1.2.3.dist-info/top_level.txt
