Metadata-Version: 2.1
Name: solidwebpush
Version: 1.2.3
Summary: 
Requires-Dist: future
Requires-Dist: py-vapid (==0.7.1)
Requires-Dist: http-ece (==0.7.0)
Requires-Dist: pyelliptic (==1.5.7)
Requires-Dist: requests (==2.20.0)
